pubmedasync/__init__.py
pubmedasync/cli.py
pubmedasync/fetch.py
pubmedasync/pubmedasync.py
pubmedasync-0.4.2.dist-info/DESCRIPTION.rst
pubmedasync-0.4.2.dist-info/METADATA
pubmedasync-0.4.2.dist-info/RECORD
pubmedasync-0.4.2.dist-info/WHEEL
pubmedasync-0.4.2.dist-info/entry_points.txt
pubmedasync-0.4.2.dist-info/metadata.json
pubmedasync-0.4.2.dist-info/top_level.txt
