Metadata-Version: 2.0
Name: pubmedasync
Version: 0.4.2
Summary: Asyncronous wrapper around PubMed api
Home-page: https://github.com/pokey/pubmedasync
Author: Pokey Rule
Author-email: pokey.rule@gmail.com
License: MIT license
Keywords: pubmedasync
Platform: UNKNOWN
Classifier: Development Status :: 2 - Pre-Alpha
Classifier: Intended Audience :: Developers
Classifier: License :: OSI Approved :: MIT License
Classifier: Natural Language :: English
Classifier: Programming Language :: Python :: 2
Classifier: Programming Language :: Python :: 2.6
Classifier: Programming Language :: Python :: 2.7
Classifier: Programming Language :: Python :: 3
Classifier: Programming Language :: Python :: 3.3
Classifier: Programming Language :: Python :: 3.4
Classifier: Programming Language :: Python :: 3.5
Requires-Dist: Click (>=6.0)
Requires-Dist: aiodns (>=1.1.1)
Requires-Dist: aiohttp (>=1.2.0)
Requires-Dist: beautifulsoup4 (>=4.5.1)
Requires-Dist: cchardet (>=1.1.1)
Requires-Dist: lxml (>=3.7.0)
Requires-Dist: tqdm (>=4.10.0)
